{
  "chunk_count": 8,
  "chunks": [
    {
      "chunk_file": "chunk-001.md",
      "chunk_index": 1,
      "heading": "最近七八期视频，每一期的读者留言，都有观众希望我们谈谈豫章书院，但是督工你一直没有回应。是觉得这个问题是偶然现象，所以不值得说吗？",
      "question": "最近七八期视频，每一期的读者留言，都有观众希望我们谈谈豫章书院，但是督工你一直没有回应。是觉得这个问题是偶然现象，所以不值得说吗？",
      "summary": "豫章学院绝对不是偶然事件",
      "usage_hint": "适合在需要节目级细节时补充与“豫章学院绝对不是偶然事件”相关的节目论据。"
    },
    {
      "chunk_file": "chunk-002.md",
      "chunk_index": 2,
      "heading": "2018年，山东济南博雅教育培训学校13岁少年王某乐被伤害致死。",
      "question": "2018年，山东济南博雅教育培训学校13岁少年王某乐被伤害致死。",
      "summary": "可以说，如果哪年没有人被这些学校虐待到死，这一年的中国倒是有点奇怪",
      "usage_hint": "适合在需要节目级细节时补充与“可以说，如果哪年没有人被这些学校虐待到死，这一年的中国倒是有”相关的节目论据。"
    },
    {
      "chunk_file": "chunk-003.md",
      "chunk_index": 3,
      "heading": "这一类培训机构的问题这么明显，为什么还可以存在十几年呢？",
      "question": "这一类培训机构的问题这么明显，为什么还可以存在十几年呢？",
      "summary": "首先，无利不起早",
      "usage_hint": "适合在需要节目级细节时补充与“首先，无利不起早”相关的节目论据。"
    },
    {
      "chunk_file": "chunk-004.md",
      "chunk_index": 4,
      "heading": "家长明知学校会体罚孩子，为什么还要送孩子去培训机构？",
      "question": "家长明知学校会体罚孩子，为什么还要送孩子去培训机构？",
      "summary": "大多数中国家庭本来也不在乎体罚，也喜欢打孩子",
      "usage_hint": "适合在需要节目级细节时补充与“大多数中国家庭本来也不在乎体罚，也喜欢打孩子”相关的节目论据。"
    },
    {
      "chunk_file": "chunk-005.md",
      "chunk_index": 5,
      "heading": "家长自己打孩子也是违法的，委托别人打更违法，社会为什么也能容忍这种私人监狱存在呢？",
      "question": "家长自己打孩子也是违法的，委托别人打更违法，社会为什么也能容忍这种私人监狱存在呢？",
      "summary": "能执行的法律才是法律，才有\"违法\"的概念",
      "usage_hint": "适合在需要节目级细节时补充与“能执行的法律才是法律，才有\"违法\"的概念”相关的节目论据。"
    },
    {
      "chunk_file": "chunk-006.md",
      "chunk_index": 6,
      "heading": "从家庭内部的决策角度，我理解了豫章书院的存在原因。但未来的中国不太可能用这样的方式教育下一代，怎样做才能消灭普遍存在的监狱式学校呢？",
      "question": "从家庭内部的决策角度，我理解了豫章书院的存在原因。但未来的中国不太可能用这样的方式教育下一代，怎样做才能消灭普遍存在的监狱式学校呢？",
      "summary": "前面我从家庭内部决策的角度分析了豫章书院的需求，现在要从全社会的角度分析，才能找到消灭豫章书院的合理方案",
      "usage_hint": "适合在需要节目级细节时补充与“前面我从家庭内部决策的角度分析了豫章书院的需求，现在要从全社”相关的节目论据。"
    },
    {
      "chunk_file": "chunk-007.md",
      "chunk_index": 7,
      "heading": "10月23日，俄罗斯两架图-160战略轰炸机从俄国本土起飞，在南非降落，俄罗斯这是在炫耀武力吗？",
      "question": "10月23日，俄罗斯两架图-160战略轰炸机从俄国本土起飞，在南非降落，俄罗斯这是在炫耀武力吗？",
      "summary": "俄罗斯肯定是想炫耀一下自己还有很多苏联遗产",
      "usage_hint": "适合在需要节目级细节时补充与“俄罗斯肯定是想炫耀一下自己还有很多苏联遗产”相关的节目论据。"
    },
    {
      "chunk_file": "chunk-008.md",
      "chunk_index": 8,
      "heading": "最近好像很多国家都举办过非洲峰会，都是邀请几十个国家的元首来国内开会。好像其他国家并不会派轰炸机给峰会助兴，俄罗斯的非洲峰会和其他国家组织的有区别吗？",
      "question": "最近好像很多国家都举办过非洲峰会，都是邀请几十个国家的元首来国内开会。好像其他国家并不会派轰炸机给峰会助兴，俄罗斯的非洲峰会和其他国家组织的有区别吗？",
      "summary": "的确最近几年非洲峰会开的不少",
      "usage_hint": "适合在需要节目级细节时补充与“的确最近几年非洲峰会开的不少”相关的节目论据。"
    }
  ],
  "date": "2019-11-08",
  "date_source": "body_explicit",
  "description": "",
  "episode_id": "main-1-100-39",
  "keywords": [],
  "source_path": "1-100/39.md",
  "source_type": "main",
  "summary": "豫章学院绝对不是偶然事件",
  "title": "【睡前消息39】如何彻底消灭“豫章书院”？"
}
