{
  "chunk_count": 1,
  "chunks": [
    {
      "chunk_file": "chunk-001.md",
      "chunk_index": 1,
      "heading": "【睡前消息919】70岁退休，丹麦人不抗议",
      "question": "",
      "summary": "以下文本为音频转录结果，存在一定错误，校对正在进行中",
      "usage_hint": "适合在需要节目级细节时补充与“以下文本为音频转录结果，存在一定错误，校对正在进行中”相关的节目论据。"
    }
  ],
  "date": "2025-06-29",
  "date_source": "body_explicit",
  "description": "丹麦退休年龄延长到70岁，邓紫棋和霉霉都在争夺自己年轻时的版权，整个世界都在开发“存量”，然而最重要的是要有年轻人来创造。",
  "episode_id": "main-901-1000-919",
  "keywords": [],
  "source_path": "901-1000/919.md",
  "source_type": "main",
  "summary": "丹麦退休年龄延长到70岁，邓紫棋和霉霉都在争夺自己年轻时的版权，整个世界都在开发“存量”，然而最重要的是要有年轻人来创造。",
  "title": "【睡前消息919】70岁退休，丹麦人不抗议"
}
